{
"autoplayBgm":false,"autoplayBgs":false,"battleback1Name":"","battleback2Name":"","bgm":{"name":"","pan":0,"pitch":100,"volume":90},"bgs":{"name":"","pan":0,"pitch":100,"volume":90},"disableDashing":false,"displayName":"runway1","encounterList":[],"encounterStep":30,"height":13,"note":"","parallaxLoopX":false,"parallaxLoopY":false,"parallaxName":"","parallaxShow":true,"parallaxSx":0,"parallaxSy":0,"scrollType":0,"specifyBattleback":false,"tilesetId":4,"width":14,
"data":[5940,5964,5964,5964,5964,5964,5964,5964,5964,5964,5964,5964,5964,5964,5960,6322,6322,6322,6322,6322,6322,6322,6322,6322,6322,6322,6322,6326,5960,6329,6328,6328,6328,6328,6328,6328,6328,6328,6328,6328,6328,6332,5960,1559,1559,1559,1559,1559,1559,1559,1559,1559,1559,1559,1559,1559,5960,1559,1559,1559,1559,1559,1559,1559,1559,1559,1559,1559,1559,1559,5960,1559,1559,1559,1559,1559,1559,1559,1559,1559,1559,1559,1559,1559,5942,5969,5969,5969,5969,5981,1559,1559,5979,5969,5969,5969,5969,5958,5960,6330,6330,6330,6330,6334,1559,1559,6331,6330,6330,6330,6330,5952,5960,1559,1559,1559,1559,1559,1559,1559,1559,1559,1559,1559,1559,5952,5960,1559,1559,1559,1559,1559,1559,1559,1559,1559,1559,1559,1559,5952,5960,1559,1559,1559,1559,1559,1559,1559,1559,1559,1559,1559,1559,5952,5960,1559,1559,1559,1559,1559,1559,1559,1559,1559,1559,1559,1559,5952,5938,5956,5956,5956,5956,5956,5956,5956,5956,5956,5956,5956,5956,5937,0,0,0,0,0,0,0,0,0,0,0,0,0,0,0,0,0,0,0,0,0,0,0,0,0,0,0,0,0,0,0,0,0,0,0,0,0,0,0,0,0,0,0,0,0,0,0,0,0,0,0,0,0,0,0,0,0,0,0,0,0,0,0,0,0,0,0,0,0,0,0,0,0,0,0,0,0,0,0,0,0,0,0,0,0,0,0,0,0,0,0,0,0,0,0,0,0,0,0,0,0,0,0,0,0,0,0,0,0,0,0,0,0,0,0,0,0,0,0,0,0,0,0,0,0,0,0,0,0,0,0,0,0,0,0,0,0,0,0,0,0,0,0,0,0,0,0,0,0,0,0,0,0,0,0,0,0,0,0,0,0,0,0,0,0,0,0,0,0,0,0,0,0,0,0,0,0,0,0,0,0,0,0,0,0,0,0,0,0,0,0,0,0,0,0,0,0,0,0,0,0,0,0,0,0,0,0,0,0,0,0,0,0,0,0,0,0,0,0,0,0,0,15,0,0,0,0,0,0,0,0,0,0,0,0,0,0,0,0,0,0,0,0,0,0,0,0,0,0,0,0,0,0,0,0,0,0,0,0,0,0,0,0,0,0,0,0,0,0,0,0,0,0,0,0,0,0,0,0,0,0,0,0,0,0,0,0,37,0,0,0,0,0,0,0,0,0,0,0,0,0,0,0,0,0,0,0,0,0,0,0,0,0,0,0,0,0,0,0,0,0,0,0,0,0,0,0,0,0,0,0,0,0,0,0,0,0,0,0,0,0,0,0,0,0,0,0,0,0,0,0,0,0,0,0,0,0,0,0,0,0,0,0,0,0,0,0,0,0,0,0,0,0,0,0,0,0,0,0,9,7,0,0,15,0,0,0,23,0,9,7,163,0,97,15,0,0,0,9,0,0,0,0,0,103,171,0,105,242,113,0,37,0,113,39,0,0,113,111,0,0,36,0,0,0,0,0,0,0,0,37,0,0,0,0,10,0,39,0,0,37,0,0,0,0,0,0,39,0,0,0,0,0,0,0,0,0,0,0,0,0,0,0,64,53,64,53,64,0,113,64,53,64,53,64,0,0,72,61,72,61,72,0,0,72,61,72,61,72,0,0,0,0,0,39,0,0,0,0,37,0,0,0,0,0,0,0,0,0,0,0,0,0,0,0,0,0,0,0,37,0,0,0,0,0,0,0,0,0,0,0,0,0,0,0,0,0,0,0,0,0,0,0,0,0,0,0,0,0,0,0,0,0,0,0,0,0,0,0,0,0,0,0,0,0,0,0,0,0,0,0,0,0,0,0,0,0,0,0,0,0,0,0,0,0,0,0,0,0,5,0,0,0,0,0,0,0,0,0,0,0,0,0,5,0,0,0,0,0,0,0,0,0,0,0,0,0,5,0,0,0,0,0,0,0,0,0,0,0,0,0,0,0,0,0,0,0,0,0,0,0,0,0,0,0,0,0,0,0,0,5,0,0,0,0,0,0,0,0,5,0,0,0,0,0,0,0,0,0,0,0,0,0,5,0,0,0,0,0,0,0,0,0,0,0,0,0,5,0,0,0,0,0,0,0,0,0,0,0,0,0,5,0,0,0,0,0,0,0,0,0,0,0,0,0,0,0,0,0,0,0,0,0,0,0,0,0,0,0,0,0,0,0,0,0,0,0,0,0,0,0,0,0,0,0,0,0,0,0,0,0,0,0,0,0,0,0,0,0,0,0,0,0,0,0,0,0,0,0,0,0,0,0,0,0,0,0,0,0,0,0,0,0,0,0,0,0,0,0,0,0,0,0,0,0,0,0,0,0,0,0,0,0,0,0,0,0,0,0,0,0,0,0,0,0,0,0,0,0,0,0,0,0,0,0,0,0,0,0,0,0,0,0,0,0,0,0,0,0,0,0,0,0,0,0,0,0,0,0,0,0,0,0,0,0,1,0,2,0,3,0,0,4,0,5,0,6,0,0,0,0,0,0,0,0,0,0,0,0,0,0,0,0,0,0,0,0,0,0,0,0,0,0,0,0,0,0,0,0,0,0,0,0,0,0,0,0,0,0,0],
"events":[
null,
{"id":1,"name":"move to starting room","note":"","pages":[{"conditions":{"actorId":1,"actorValid":false,"itemId":1,"itemValid":false,"selfSwitchCh":"A","selfSwitchValid":false,"switch1Id":1,"switch1Valid":false,"switch2Id":1,"switch2Valid":false,"variableId":1,"variableValid":false,"variableValue":0},"directionFix":false,"image":{"characterIndex":0,"characterName":"","direction":2,"pattern":0,"tileId":0},"list":[{"code":201,"indent":0,"parameters":[0,1,10,11,0,0]},{"code":241,"indent":0,"parameters":[{"name":"DUNGEON THEME","volume":10,"pitch":120,"pan":0}]},{"code":0,"indent":0,"parameters":[]}],"moveFrequency":3,"moveRoute":{"list":[{"code":0,"parameters":[]}],"repeat":true,"skippable":false,"wait":false},"moveSpeed":3,"moveType":0,"priorityType":0,"stepAnime":false,"through":false,"trigger":0,"walkAnime":true}],"x":1,"y":5},
{"id":2,"name":"tutor stage 1","note":"","pages":[{"conditions":{"actorId":1,"actorValid":false,"itemId":1,"itemValid":false,"selfSwitchCh":"A","selfSwitchValid":false,"switch1Id":1,"switch1Valid":false,"switch2Id":1,"switch2Valid":false,"variableId":1,"variableValid":false,"variableValue":0},"directionFix":false,"image":{"tileId":0,"characterName":"Actor3","direction":2,"pattern":1,"characterIndex":3},"list":[{"code":101,"indent":0,"parameters":["Actor3",3,0,2,"player"]},{"code":401,"indent":0,"parameters":["Ohh! Hello Player"]},{"code":101,"indent":0,"parameters":["Actor3",3,0,2,"???"]},{"code":401,"indent":0,"parameters":["I'm just a virtual image to guide you as your "]},{"code":401,"indent":0,"parameters":["teacher"]},{"code":101,"indent":0,"parameters":["Actor3",3,0,2,"Teacher image"]},{"code":401,"indent":0,"parameters":["I have create some statue here and these may"]},{"code":401,"indent":0,"parameters":["help you to remember your power."]},{"code":101,"indent":0,"parameters":["role1",0,0,2,"player"]},{"code":401,"indent":0,"parameters":["My power?"]},{"code":101,"indent":0,"parameters":["Actor3",3,0,2,"Teacher image"]},{"code":401,"indent":0,"parameters":["Yes! Until then, you will see in the next stage."]},{"code":401,"indent":0,"parameters":["Good luck to you."]},{"code":101,"indent":0,"parameters":["role1",0,0,2,"player"]},{"code":401,"indent":0,"parameters":["Wait! What should I do?"]},{"code":101,"indent":0,"parameters":["Actor3",3,0,2,"Teacher image"]},{"code":401,"indent":0,"parameters":["The road ahead requires you to apply your "]},{"code":401,"indent":0,"parameters":["knowledge of java to solve a variety of "]},{"code":401,"indent":0,"parameters":["difficult problems."]},{"code":0,"indent":0,"parameters":[]}],"moveFrequency":3,"moveRoute":{"list":[{"code":0,"parameters":[]}],"repeat":true,"skippable":false,"wait":false},"moveSpeed":3,"moveType":0,"priorityType":1,"stepAnime":false,"through":false,"trigger":0,"walkAnime":true}],"x":7,"y":11},
{"id":3,"name":"move to stage 1","note":"","pages":[{"conditions":{"actorId":1,"actorValid":false,"itemId":1,"itemValid":false,"selfSwitchCh":"A","selfSwitchValid":false,"switch1Id":1,"switch1Valid":false,"switch2Id":1,"switch2Valid":false,"variableId":1,"variableValid":false,"variableValue":0},"directionFix":false,"image":{"characterIndex":0,"characterName":"","direction":2,"pattern":0,"tileId":0},"list":[{"code":201,"indent":0,"parameters":[0,3,4,13,0,0]},{"code":0,"indent":0,"parameters":[]}],"moveFrequency":3,"moveRoute":{"list":[{"code":0,"parameters":[]}],"repeat":true,"skippable":false,"wait":false},"moveSpeed":3,"moveType":0,"priorityType":0,"stepAnime":false,"through":false,"trigger":0,"walkAnime":true}],"x":13,"y":2},
{"id":4,"name":"msg to next stage","note":"","pages":[{"conditions":{"actorId":1,"actorValid":false,"itemId":1,"itemValid":false,"selfSwitchCh":"A","selfSwitchValid":false,"switch1Id":1,"switch1Valid":false,"switch2Id":1,"switch2Valid":false,"variableId":1,"variableValid":false,"variableValue":0},"directionFix":false,"image":{"characterIndex":0,"characterName":"","direction":2,"pattern":0,"tileId":0},"list":[{"code":101,"indent":0,"parameters":["role1",0,2,2,"player"]},{"code":401,"indent":0,"parameters":["Maybe this is the way to the next level."]},{"code":0,"indent":0,"parameters":[]}],"moveFrequency":3,"moveRoute":{"list":[{"code":0,"parameters":[]}],"repeat":true,"skippable":false,"wait":false},"moveSpeed":3,"moveType":0,"priorityType":0,"stepAnime":false,"through":false,"trigger":1,"walkAnime":true}],"x":13,"y":3},
{"id":5,"name":"teaching 1","note":"","pages":[{"conditions":{"actorId":1,"actorValid":false,"itemId":1,"itemValid":false,"selfSwitchCh":"A","selfSwitchValid":false,"switch1Id":1,"switch1Valid":false,"switch2Id":1,"switch2Valid":false,"variableId":1,"variableValid":false,"variableValue":0},"directionFix":false,"image":{"characterIndex":0,"characterName":"","direction":2,"pattern":0,"tileId":0},"list":[{"code":101,"indent":0,"parameters":["",0,1,1,""]},{"code":401,"indent":0,"parameters":["\\{Basic syntax"]},{"code":101,"indent":0,"parameters":["",0,0,2,""]},{"code":401,"indent":0,"parameters":["In java programming, a semi-colon “;” is needed at the end "]},{"code":401,"indent":0,"parameters":["of each statements."]},{"code":101,"indent":0,"parameters":["",0,0,2,""]},{"code":401,"indent":0,"parameters":["We would need a brace pair “{ }” for a block of codes, e.g. "]},{"code":401,"indent":0,"parameters":["an if-statement ,a while loop or a class. "]},{"code":101,"indent":0,"parameters":["",0,0,2,""]},{"code":401,"indent":0,"parameters":["To run your program when calling, you would need to define a"]},{"code":401,"indent":0,"parameters":["main function by using "]},{"code":401,"indent":0,"parameters":["“public static void main(String[] args)”."]},{"code":101,"indent":0,"parameters":["",0,0,2,""]},{"code":401,"indent":0,"parameters":["This is the method that would actually run."]},{"code":250,"indent":0,"parameters":[{"name":"Bell3","volume":5,"pitch":150,"pan":0}]},{"code":101,"indent":0,"parameters":["",0,0,2,""]},{"code":401,"indent":0,"parameters":["public class tutoria1 {"]},{"code":401,"indent":0,"parameters":["    public static void main(String[] args){"]},{"code":401,"indent":0,"parameters":["\t\tSystem.out.println(\"Hi\");}"]},{"code":401,"indent":0,"parameters":["}"]},{"code":101,"indent":0,"parameters":["",0,0,2,""]},{"code":401,"indent":0,"parameters":["Here is a sample code. In line 2, the main method is "]},{"code":401,"indent":0,"parameters":["declared. As you can see, there is a “{“ following the class"]},{"code":401,"indent":0,"parameters":["and the main function. It would be paired with the “}” in "]},{"code":401,"indent":0,"parameters":["line 4. Also, after the statement in line 3, there is a semi-colon."]},{"code":0,"indent":0,"parameters":[]}],"moveFrequency":3,"moveRoute":{"list":[{"code":0,"parameters":[]}],"repeat":true,"skippable":false,"wait":false},"moveSpeed":3,"moveType":0,"priorityType":0,"stepAnime":false,"through":false,"trigger":0,"walkAnime":true}],"x":1,"y":9},
{"id":6,"name":"teaching 2","note":"","pages":[{"conditions":{"actorId":1,"actorValid":false,"itemId":1,"itemValid":false,"selfSwitchCh":"A","selfSwitchValid":false,"switch1Id":1,"switch1Valid":false,"switch2Id":1,"switch2Valid":false,"variableId":1,"variableValid":false,"variableValue":0},"directionFix":false,"image":{"characterIndex":0,"characterName":"","direction":2,"pattern":0,"tileId":0},"list":[{"code":101,"indent":0,"parameters":["",0,1,1,""]},{"code":401,"indent":0,"parameters":["\\{Printing message"]},{"code":101,"indent":0,"parameters":["",0,0,2,""]},{"code":401,"indent":0,"parameters":["If you want to print a message, you may use "]},{"code":401,"indent":0,"parameters":["“System.out.println()”. "]},{"code":101,"indent":0,"parameters":["",0,0,2,""]},{"code":401,"indent":0,"parameters":["If you want to print the exact message, you would need to "]},{"code":401,"indent":0,"parameters":["put the message in a “ ”. "]},{"code":101,"indent":0,"parameters":["",0,0,2,""]},{"code":401,"indent":0,"parameters":["The output after it would start on a new line. If you want "]},{"code":401,"indent":0,"parameters":["the latter output start on the same line, you may use "]},{"code":401,"indent":0,"parameters":["“System.out.print()”."]},{"code":101,"indent":0,"parameters":["",0,0,2,""]},{"code":401,"indent":0,"parameters":["If you want your message to start on a new line, you would "]},{"code":401,"indent":0,"parameters":["need to use “\\n”."]},{"code":250,"indent":0,"parameters":[{"name":"Bell3","volume":10,"pitch":150,"pan":0}]},{"code":101,"indent":0,"parameters":["",0,0,2,""]},{"code":401,"indent":0,"parameters":["public class tutorial2 {"]},{"code":401,"indent":0,"parameters":["    public static void main(String[] args){"]},{"code":401,"indent":0,"parameters":["\t\tSystem.out.println(\"Hi\\nHello”);"]},{"code":401,"indent":0,"parameters":["        System.out.print(“GM”)}}"]},{"code":101,"indent":0,"parameters":["",0,0,2,""]},{"code":401,"indent":0,"parameters":["In this program, the message “Hi” would be printed on line 1"]},{"code":401,"indent":0,"parameters":["Since there is a “\\n”, “Hello” would be printed on line2."]},{"code":101,"indent":0,"parameters":["",0,0,2,""]},{"code":401,"indent":0,"parameters":["System.out.println() would make the latter output start on a"]},{"code":401,"indent":0,"parameters":["new line, so the message “GM” would be started on line 3."]},{"code":0,"indent":0,"parameters":[]}],"moveFrequency":3,"moveRoute":{"list":[{"code":0,"parameters":[]}],"repeat":true,"skippable":false,"wait":false},"moveSpeed":3,"moveType":0,"priorityType":0,"stepAnime":false,"through":false,"trigger":0,"walkAnime":true}],"x":3,"y":9},
{"id":7,"name":"teaching 3","note":"","pages":[{"conditions":{"actorId":1,"actorValid":false,"itemId":1,"itemValid":false,"selfSwitchCh":"A","selfSwitchValid":false,"switch1Id":1,"switch1Valid":false,"switch2Id":1,"switch2Valid":false,"variableId":1,"variableValid":false,"variableValue":0},"directionFix":false,"image":{"characterIndex":0,"characterName":"","direction":2,"pattern":0,"tileId":0},"list":[{"code":101,"indent":0,"parameters":["",0,1,1,""]},{"code":401,"indent":0,"parameters":["\\{Data type"]},{"code":101,"indent":0,"parameters":["",0,0,2,""]},{"code":401,"indent":0,"parameters":["When you declare a variable, you would need to declare its "]},{"code":401,"indent":0,"parameters":["data type, e.g. “int” for integer, “String” for text, "]},{"code":401,"indent":0,"parameters":["“double” for number."]},{"code":101,"indent":0,"parameters":["",0,0,2,""]},{"code":401,"indent":0,"parameters":["There are different kinds of data type. Primitive types "]},{"code":401,"indent":0,"parameters":["(e.g. int, boolean) can be assigned directly. "]},{"code":401,"indent":0,"parameters":["Reference types (e.g. String, array) would need a “new” "]},{"code":401,"indent":0,"parameters":["and call the constructor when you assign a value to it."]},{"code":101,"indent":0,"parameters":["",0,0,2,""]},{"code":401,"indent":0,"parameters":["In order to assign a value to a variable, we would use “=”. "]},{"code":401,"indent":0,"parameters":["You don’t have to assign a value to the variable right after "]},{"code":401,"indent":0,"parameters":["declaration. However, it has to be assigned before calling."]},{"code":250,"indent":0,"parameters":[{"name":"Coin","volume":10,"pitch":150,"pan":0}]},{"code":101,"indent":0,"parameters":["",0,0,2,""]},{"code":401,"indent":0,"parameters":["int a;"]},{"code":401,"indent":0,"parameters":["a = 1;"]},{"code":401,"indent":0,"parameters":["int b = 5;"]},{"code":401,"indent":0,"parameters":["String c = new String(“Hi”);"]},{"code":101,"indent":0,"parameters":["",0,0,2,""]},{"code":401,"indent":0,"parameters":["In the sample, a and b are both int type. Their values are 1"]},{"code":401,"indent":0,"parameters":["and 5 respectively. The String “Hi” is assigned to c. "]},{"code":401,"indent":0,"parameters":["You would need to write “new String()” for it."]},{"code":0,"indent":0,"parameters":[]}],"moveFrequency":3,"moveRoute":{"list":[{"code":0,"parameters":[]}],"repeat":true,"skippable":false,"wait":false},"moveSpeed":3,"moveType":0,"priorityType":0,"stepAnime":false,"through":false,"trigger":0,"walkAnime":true}],"x":5,"y":9},
{"id":8,"name":"teaching 4","note":"","pages":[{"conditions":{"actorId":1,"actorValid":false,"itemId":1,"itemValid":false,"selfSwitchCh":"A","selfSwitchValid":false,"switch1Id":1,"switch1Valid":false,"switch2Id":1,"switch2Valid":false,"variableId":1,"variableValid":false,"variableValue":0},"directionFix":false,"image":{"characterIndex":0,"characterName":"","direction":2,"pattern":0,"tileId":0},"list":[{"code":101,"indent":0,"parameters":["",0,1,1,""]},{"code":401,"indent":0,"parameters":["\\{Operators"]},{"code":101,"indent":0,"parameters":["",0,0,2,""]},{"code":401,"indent":0,"parameters":["Arithmetic operators are symbols that you can use for doing "]},{"code":401,"indent":0,"parameters":["calculation. “+”, “-“, “*”, “/” are four basic operators "]},{"code":401,"indent":0,"parameters":["that we are probably familiar with."]},{"code":101,"indent":0,"parameters":["",0,0,2,""]},{"code":401,"indent":0,"parameters":["“%” is an operator that could give the remainder after division. "]},{"code":401,"indent":0,"parameters":["For example, the result of 17%4 is 1. If you want to increase "]},{"code":401,"indent":0,"parameters":["the value of x by 1, you could write it as x=x+1 or x+=1."]},{"code":101,"indent":0,"parameters":["",0,0,2,""]},{"code":401,"indent":0,"parameters":["Equality and logical operators can return a boolean (true or"]},{"code":401,"indent":0,"parameters":[" false). “<”, “>”, “<=”, “>=” works just like in "]},{"code":401,"indent":0,"parameters":["mathematics. "]},{"code":101,"indent":0,"parameters":["",0,0,2,""]},{"code":401,"indent":0,"parameters":["“instanceof” can return if a variable belongs to a specific "]},{"code":401,"indent":0,"parameters":["type. “==” and “!=” represent equal and not equal."]},{"code":101,"indent":0,"parameters":["",0,0,2,""]},{"code":401,"indent":0,"parameters":["“&&” and “||” represent Logical AND (true if both statement "]},{"code":401,"indent":0,"parameters":["are true) and Logical OR (true if at least one of the "]},{"code":401,"indent":0,"parameters":["statement is true)."]},{"code":250,"indent":0,"parameters":[{"name":"Save2","volume":20,"pitch":100,"pan":0}]},{"code":101,"indent":0,"parameters":["",0,0,2,""]},{"code":401,"indent":0,"parameters":["int x = 10;"]},{"code":401,"indent":0,"parameters":["x = x+5;"]},{"code":401,"indent":0,"parameters":["boolean y = x == 15;"]},{"code":101,"indent":0,"parameters":["",0,0,2,""]},{"code":401,"indent":0,"parameters":["In the sample, the initial value of x is 10. It is then "]},{"code":401,"indent":0,"parameters":["increased by 5. Since the value of x is equal to 15, the "]},{"code":401,"indent":0,"parameters":["value of y would be true."]},{"code":0,"indent":0,"parameters":[]}],"moveFrequency":3,"moveRoute":{"list":[{"code":0,"parameters":[]}],"repeat":true,"skippable":false,"wait":false},"moveSpeed":3,"moveType":0,"priorityType":0,"stepAnime":false,"through":false,"trigger":0,"walkAnime":true}],"x":8,"y":9},
{"id":9,"name":"teaching 5","note":"","pages":[{"conditions":{"actorId":1,"actorValid":false,"itemId":1,"itemValid":false,"selfSwitchCh":"A","selfSwitchValid":false,"switch1Id":1,"switch1Valid":false,"switch2Id":1,"switch2Valid":false,"variableId":1,"variableValid":false,"variableValue":0},"directionFix":false,"image":{"characterIndex":0,"characterName":"","direction":2,"pattern":0,"tileId":0},"list":[{"code":101,"indent":0,"parameters":["",0,1,1,""]},{"code":401,"indent":0,"parameters":["\\{Precedence"]},{"code":101,"indent":0,"parameters":["",0,0,2,""]},{"code":401,"indent":0,"parameters":["In general, the priority is arithmetic operators > equality "]},{"code":401,"indent":0,"parameters":["operators > logical operators > assignment operators."]},{"code":101,"indent":0,"parameters":["",0,0,2,""]},{"code":401,"indent":0,"parameters":["The details can refer to the above table. For different operators "]},{"code":401,"indent":0,"parameters":["of the same precedence, it would run from left to right. "]},{"code":401,"indent":0,"parameters":["Statement within the blanket would always has the highest "]},{"code":401,"indent":0,"parameters":["precedence."]},{"code":250,"indent":0,"parameters":[{"name":"Bell1","volume":5,"pitch":150,"pan":0}]},{"code":101,"indent":0,"parameters":["",0,0,2,""]},{"code":401,"indent":0,"parameters":["boolean x = true;"]},{"code":401,"indent":0,"parameters":["boolean y = false;"]},{"code":401,"indent":0,"parameters":["boolean z = true;"]},{"code":401,"indent":0,"parameters":["boolean a = (x || y) && z;"]},{"code":101,"indent":0,"parameters":["",0,0,2,""]},{"code":401,"indent":0,"parameters":["In the sample, since (x || y) is inside a blanket, it would "]},{"code":401,"indent":0,"parameters":["have higher precedence than && even though && has higher "]},{"code":401,"indent":0,"parameters":["precedence. So a is true."]},{"code":0,"indent":0,"parameters":[]}],"moveFrequency":3,"moveRoute":{"list":[{"code":0,"parameters":[]}],"repeat":true,"skippable":false,"wait":false},"moveSpeed":3,"moveType":0,"priorityType":0,"stepAnime":false,"through":false,"trigger":0,"walkAnime":true}],"x":10,"y":9},
{"id":10,"name":"teaching 6","note":"","pages":[{"conditions":{"actorId":1,"actorValid":false,"itemId":1,"itemValid":false,"selfSwitchCh":"A","selfSwitchValid":false,"switch1Id":1,"switch1Valid":false,"switch2Id":1,"switch2Valid":false,"variableId":1,"variableValid":false,"variableValue":0},"directionFix":false,"image":{"characterIndex":0,"characterName":"","direction":2,"pattern":0,"tileId":0},"list":[{"code":101,"indent":0,"parameters":["",0,1,1,""]},{"code":401,"indent":0,"parameters":["\\{Promotion rule"]},{"code":101,"indent":0,"parameters":["",0,0,2,""]},{"code":401,"indent":0,"parameters":["In java, you could use “+” to add two variable together for "]},{"code":401,"indent":0,"parameters":["some data type like int, double and String."]},{"code":101,"indent":0,"parameters":["",0,0,2,""]},{"code":401,"indent":0,"parameters":["When int type is doing addition with other data type, it "]},{"code":401,"indent":0,"parameters":["would be promoted to the type it is doing addition with."]},{"code":250,"indent":0,"parameters":[{"name":"Bell2","volume":10,"pitch":150,"pan":0}]},{"code":101,"indent":0,"parameters":["",0,0,2,""]},{"code":401,"indent":0,"parameters":["int a = 10;"]},{"code":401,"indent":0,"parameters":["String b = new String(“AB”)"]},{"code":401,"indent":0,"parameters":["int c = 20;"]},{"code":401,"indent":0,"parameters":["System.out.println(a + c + b);"]},{"code":101,"indent":0,"parameters":["",0,0,2,""]},{"code":401,"indent":0,"parameters":["First, the code a + c would run, giving a result of 30. "]},{"code":401,"indent":0,"parameters":["Then 30 would be added with b. "]},{"code":101,"indent":0,"parameters":["",0,0,2,""]},{"code":401,"indent":0,"parameters":["Since b is a String, 30 (int type) would be promoted to “30” "]},{"code":401,"indent":0,"parameters":["(String type). The final output of the program would be “30AB”."]},{"code":0,"indent":0,"parameters":[]}],"moveFrequency":3,"moveRoute":{"list":[{"code":0,"parameters":[]}],"repeat":true,"skippable":false,"wait":false},"moveSpeed":3,"moveType":0,"priorityType":0,"stepAnime":false,"through":false,"trigger":0,"walkAnime":true}],"x":12,"y":9},
{"id":11,"name":"Cutscene of tutor","note":"","pages":[{"conditions":{"actorId":1,"actorValid":false,"itemId":1,"itemValid":false,"selfSwitchCh":"A","selfSwitchValid":false,"switch1Id":1,"switch1Valid":false,"switch2Id":1,"switch2Valid":false,"variableId":1,"variableValid":false,"variableValue":0},"directionFix":false,"image":{"characterIndex":0,"characterName":"","direction":2,"pattern":0,"tileId":0},"list":[{"code":205,"indent":0,"parameters":[2,{"list":[{"code":2,"indent":null},{"code":4,"indent":null},{"code":4,"indent":null},{"code":0}],"repeat":false,"skippable":false,"wait":true}]},{"code":505,"indent":0,"parameters":[{"code":2,"indent":null}]},{"code":505,"indent":0,"parameters":[{"code":4,"indent":null}]},{"code":505,"indent":0,"parameters":[{"code":4,"indent":null}]},{"code":213,"indent":0,"parameters":[-1,1,true]},{"code":101,"indent":0,"parameters":["role1",0,0,2,"player"]},{"code":401,"indent":0,"parameters":["Who are you?"]},{"code":101,"indent":0,"parameters":["role1",0,0,2,"player"]},{"code":401,"indent":0,"parameters":["And why you here, its dangers here"]},{"code":101,"indent":0,"parameters":["Actor3",3,0,2,"???"]},{"code":401,"indent":0,"parameters":["I'm just a virtual image of your teacher."]},{"code":101,"indent":0,"parameters":["Actor3",3,0,2,"Teacher image"]},{"code":401,"indent":0,"parameters":["I have create some statue here and these may"]},{"code":401,"indent":0,"parameters":["help you to remember your power."]},{"code":101,"indent":0,"parameters":["role1",0,0,2,"player"]},{"code":401,"indent":0,"parameters":["My power?"]},{"code":101,"indent":0,"parameters":["Actor3",3,0,2,"Teacher image"]},{"code":401,"indent":0,"parameters":["Yes! Next time you see me will in next stage."]},{"code":401,"indent":0,"parameters":["Good luck for you."]},{"code":101,"indent":0,"parameters":["role1",0,0,2,"player"]},{"code":401,"indent":0,"parameters":["Wait! What should I do?"]},{"code":101,"indent":0,"parameters":["Actor3",3,0,2,"Teacher image"]},{"code":401,"indent":0,"parameters":["The road ahead requires you to apply your "]},{"code":401,"indent":0,"parameters":["knowledge of java to solve a variety of "]},{"code":401,"indent":0,"parameters":["difficult problems."]},{"code":205,"indent":0,"parameters":[2,{"list":[{"code":1,"indent":null},{"code":1,"indent":null},{"code":3,"indent":null},{"code":16,"indent":null},{"code":0}],"repeat":false,"skippable":false,"wait":true}]},{"code":505,"indent":0,"parameters":[{"code":1,"indent":null}]},{"code":505,"indent":0,"parameters":[{"code":1,"indent":null}]},{"code":505,"indent":0,"parameters":[{"code":3,"indent":null}]},{"code":505,"indent":0,"parameters":[{"code":16,"indent":null}]},{"code":123,"indent":0,"parameters":["A",0]},{"code":0,"indent":0,"parameters":[]}],"moveFrequency":3,"moveRoute":{"list":[{"code":0,"parameters":[]}],"repeat":true,"skippable":false,"wait":false},"moveSpeed":3,"moveType":0,"priorityType":0,"stepAnime":false,"through":false,"trigger":1,"walkAnime":true},{"conditions":{"actorId":1,"actorValid":false,"itemId":1,"itemValid":false,"selfSwitchCh":"A","selfSwitchValid":true,"switch1Id":1,"switch1Valid":false,"switch2Id":1,"switch2Valid":false,"variableId":1,"variableValid":false,"variableValue":0},"directionFix":false,"image":{"tileId":0,"characterName":"","direction":2,"pattern":0,"characterIndex":3},"list":[{"code":0,"indent":0,"parameters":[]}],"moveFrequency":3,"moveRoute":{"list":[{"code":0,"parameters":[]}],"repeat":true,"skippable":false,"wait":false},"moveSpeed":3,"moveType":0,"priorityType":0,"stepAnime":false,"through":false,"trigger":0,"walkAnime":true}],"x":6,"y":8}
]
}